dango/__init__.py
dango/cli/__init__.py
dango/cli/db_helpers.py
dango/cli/env_helpers.py
dango/cli/init.py
dango/cli/main.py
dango/cli/model_wizard.py
dango/cli/oauth.py
dango/cli/schema_manager.py
dango/cli/source_wizard.py
dango/cli/utils.py
dango/cli/validate.py
dango/cli/wizard.py
dango/config/__init__.py
dango/config/credentials.py
dango/config/exceptions.py
dango/config/loader.py
dango/config/models.py
dango/ingestion/__init__.py
dango/ingestion/csv_loader.py
dango/ingestion/dlt_runner.py
dango/ingestion/dlt_sources/__init__.py
dango/ingestion/dlt_sources/airtable/README.md
dango/ingestion/dlt_sources/airtable/__init__.py
dango/ingestion/dlt_sources/asana_dlt/README.md
dango/ingestion/dlt_sources/asana_dlt/__init__.py
dango/ingestion/dlt_sources/asana_dlt/helpers.py
dango/ingestion/dlt_sources/asana_dlt/settings.py
dango/ingestion/dlt_sources/chess/README.md
dango/ingestion/dlt_sources/chess/__init__.py
dango/ingestion/dlt_sources/chess/helpers.py
dango/ingestion/dlt_sources/chess/settings.py
dango/ingestion/dlt_sources/facebook_ads/README.md
dango/ingestion/dlt_sources/facebook_ads/__init__.py
dango/ingestion/dlt_sources/facebook_ads/exceptions.py
dango/ingestion/dlt_sources/facebook_ads/helpers.py
dango/ingestion/dlt_sources/facebook_ads/settings.py
dango/ingestion/dlt_sources/facebook_ads/utils.py
dango/ingestion/dlt_sources/freshdesk/README.md
dango/ingestion/dlt_sources/freshdesk/__init__.py
dango/ingestion/dlt_sources/freshdesk/freshdesk_client.py
dango/ingestion/dlt_sources/freshdesk/settings.py
dango/ingestion/dlt_sources/github/README.md
dango/ingestion/dlt_sources/github/__init__.py
dango/ingestion/dlt_sources/github/helpers.py
dango/ingestion/dlt_sources/github/queries.py
dango/ingestion/dlt_sources/github/settings.py
dango/ingestion/dlt_sources/google_ads/README.md
dango/ingestion/dlt_sources/google_ads/__init__.py
dango/ingestion/dlt_sources/google_ads/setup_script_gcp_oauth.py
dango/ingestion/dlt_sources/google_ads/helpers/__init__.py
getdango-0.1.1.dist-info/licenses/LICENSE
getdango-0.1.1.dist-info/METADATA
getdango-0.1.1.dist-info/WHEEL
getdango-0.1.1.dist-info/entry_points.txt
getdango-0.1.1.dist-info/top_level.txt
getdango-0.1.1.dist-info/RECORD
