Metadata-Version: 2.4
Name: getdango
Version: 0.1.1
Summary: Open source data platform built with production-grade tools - dlt, dbt, DuckDB, and Metabase
Author: Dango Team
License: Apache-2.0
Project-URL: Homepage, https://getdango.dev
Project-URL: Documentation, https://docs.getdango.dev
Project-URL: Repository, https://github.com/getdango/dango
Project-URL: Issues, https://github.com/getdango/dango/issues
Keywords: data,analytics,dbt,duckdb,metabase,dlt,etl,data-platform,open-source
Classifier: Development Status :: 3 - Alpha
Classifier: Intended Audience :: Developers
Classifier: Intended Audience :: Information Technology
Classifier: License :: OSI Approved :: Apache Software License
Classifier: Programming Language :: Python :: 3
Classifier: Programming Language :: Python :: 3.10
Classifier: Programming Language :: Python :: 3.11
Classifier: Programming Language :: Python :: 3.12
Classifier: Topic :: Database
Classifier: Topic :: Scientific/Engineering :: Information Analysis
Requires-Python: <3.13,>=3.10
License-File: LICENSE
Requires-Dist: duckdb~=1.4.0
Requires-Dist: dbt-core~=1.10.0
Requires-Dist: dbt-duckdb~=1.10.0
Requires-Dist: dlt[duckdb]<2.0,>=1.17.0
Requires-Dist: click>=8.1.7
Requires-Dist: pyyaml>=6.0.1
Requires-Dist: pydantic>=2.0.0
Requires-Dist: python-dotenv>=1.0.0
Requires-Dist: jinja2>=3.1.4
Requires-Dist: watchdog>=5.0.0
Requires-Dist: rich>=13.7.0
Requires-Dist: inquirer>=3.4.0
Requires-Dist: requests>=2.31.0
Requires-Dist: httpx>=0.27.0
Requires-Dist: fastapi>=0.109.0
Requires-Dist: uvicorn[standard]>=0.27.0
Requires-Dist: python-multipart>=0.0.9
Requires-Dist: websockets>=12.0
Requires-Dist: aiofiles>=23.2.0
Requires-Dist: psutil>=5.9.0
Requires-Dist: keyring>=24.0.0
Requires-Dist: cryptography>=41.0.0
Requires-Dist: toml>=0.10.2
Requires-Dist: google-api-python-client>=2.100.0
Requires-Dist: google-auth-oauthlib>=1.0.0
Requires-Dist: google-auth>=2.22.0
Provides-Extra: dev
Requires-Dist: pytest>=8.0.0; extra == "dev"
Requires-Dist: pytest-cov>=5.0.0; extra == "dev"
Requires-Dist: black>=24.0.0; extra == "dev"
Requires-Dist: ruff>=0.6.0; extra == "dev"
Requires-Dist: mypy>=1.11.0; extra == "dev"
Dynamic: license-file
